setup.cfg
setup.py
fs448582ztm/__init__.py
fs448582ztm/ztm_api_wrapper.py
fs448582ztm/ztm_classes.py
fs448582ztm/ztm_fetch_data.py
fs448582ztm/ztm_plots.py
fs448582ztm.egg-info/PKG-INFO
fs448582ztm.egg-info/SOURCES.txt
fs448582ztm.egg-info/dependency_links.txt
fs448582ztm.egg-info/not-zip-safe
fs448582ztm.egg-info/requires.txt
fs448582ztm.egg-info/top_level.txt