Metadata-Version: 2.1
Name: fs448582ztm
Version: 0.0
Summary: University project about analizing ztm buses
Home-page: UNKNOWN
Author-email: fs448582@students.mimuw.edu.pl
License: UNKNOWN
Platform: UNKNOWN
